pyfb_reporting/__init__.py
pyfb_reporting/admin.py
pyfb_reporting/api.py
pyfb_reporting/apps.py
pyfb_reporting/forms.py
pyfb_reporting/models.py
pyfb_reporting/serializers.py
pyfb_reporting/urls.py
pyfb_reporting/views.py
pyfb_reporting/management/commands/dailystats.py
pyfb_reporting/migrations/0001_initial.py
pyfb_reporting/migrations/0002_auto_20190521_0820.py
pyfb_reporting/migrations/0003_auto_20190618_1639.py
pyfb_reporting/migrations/0004_auto_20190621_1449.py
pyfb_reporting/migrations/0005_remove_cdr_chan_name.py
pyfb_reporting/migrations/0006_cdr_route_json.py
pyfb_reporting/migrations/0007_auto_20200219_1905.py
pyfb_reporting/migrations/0008_auto_20200520_1646.py
pyfb_reporting/migrations/0009_auto_20200526_1724.py
pyfb_reporting/migrations/0010_auto_20200527_0725.py
pyfb_reporting/migrations/0011_auto_20200529_1349.py
pyfb_reporting/migrations/0012_auto_20200529_1349.py
pyfb_reporting/migrations/0013_auto_20200529_1412.py
pyfb_reporting/migrations/0014_auto_20200610_1614.py
pyfb_reporting/migrations/__init__.py
pyfb_reporting/static/css/pyfb_reporting.css
pyfb_reporting/static/js/pyfb_reporting.js
pyfb_reporting/templates/pyfb_reporting/base.html
pyfb_reporting-1.2.1.dist-info/AUTHORS.rst
pyfb_reporting-1.2.1.dist-info/LICENSE
pyfb_reporting-1.2.1.dist-info/METADATA
pyfb_reporting-1.2.1.dist-info/WHEEL
pyfb_reporting-1.2.1.dist-info/top_level.txt
pyfb_reporting-1.2.1.dist-info/RECORD
