Metadata-Version: 2.1
Name: pyfb-reporting
Version: 1.2.1
Summary: Reporting application for PyFB project
Home-page: https://www.pyfreebilling.com
Author: Mathias WOLFF
Author-email: mathias@celea.org
License: MIT
Keywords: pyfb-reporting
Platform: UNKNOWN
Classifier: Development Status :: 5 - Production/Stable
Classifier: Framework :: Django :: 2.2
Classifier: Intended Audience :: Developers
Classifier: License :: OSI Approved :: MIT License
Classifier: Natural Language :: English
Classifier: Programming Language :: Python :: 3.6
Classifier: Programming Language :: Python :: 3.7
Classifier: Programming Language :: Python :: 3.8
Requires-Dist: django (<3,>=2.2.12)
Requires-Dist: django-model-utils (>=2.0)
Requires-Dist: django-import-export (>=2.1.0)
Requires-Dist: djangorestframework (>=3.7.7)
Requires-Dist: django-crispy-forms (>=1.7.0)
Requires-Dist: pygments (>=2.4.2)
Requires-Dist: pyfb-company (>=1.0.0)
Requires-Dist: pyfb-endpoint (>=1.1.0)
Requires-Dist: pyfb-rating (>=1.0.0)
Requires-Dist: pyfb-routing (>=1.0.1)
Requires-Dist: pyfb-direction (>=1.0.4)
Requires-Dist: pyfb-kamailio (>=1.2.1)
Requires-Dist: pyfb-did (>=1.0.3)
